abusify_id/.env
abusify_id/__init__.py
abusify_id/abusiveword_detector.py
abusify_id/abusiveword_filter.py
abusify_id/model.pkl
abusify_id/predict_abusiveness.py
abusify_id/tfidf_vectorizer.pkl
abusify_id-0.13.dist-info/METADATA
abusify_id-0.13.dist-info/WHEEL
abusify_id-0.13.dist-info/top_level.txt
abusify_id-0.13.dist-info/RECORD
