Metadata-Version: 2.1
Name: abusify-id
Version: 0.13
Summary: Abusiveness Verification in Bahasa Indonesia
Requires-Dist: scikit-learn
Requires-Dist: pandas
Requires-Dist: nltk
Requires-Dist: pymysql
Requires-Dist: python-decouple
Requires-Dist: fuzzywuzzy
Requires-Dist: python-Levenshtein
